lib_toggl/__init__.py
lib_toggl/account.py
lib_toggl/client.py
lib_toggl/const.py
lib_toggl/organization.py
lib_toggl/tags.py
lib_toggl/time_entries.py
lib_toggl/workspace.py
lib_toggl-0.2.1.dist-info/METADATA
lib_toggl-0.2.1.dist-info/WHEEL
lib_toggl-0.2.1.dist-info/licenses/LICENSE
lib_toggl-0.2.1.dist-info/RECORD
