Metadata-Version: 2.4
Name: lib-toggl
Version: 0.2.1
Summary: Asynchronous Python library for the Toggl API.
Author: Karl Quinsalnd
License-File: LICENSE
Requires-Python: <4.0,>=3.13
Requires-Dist: aiodns<4.0.0,>=3.1.1
Requires-Dist: aiohttp<4.0.0,>=3.9.1
Requires-Dist: certifi<2026.0.0,>=2023.11.17
Requires-Dist: pydantic<3.0.0,>=1.10.2
Requires-Dist: pyrfc3339<3.0,>=1.1
